{"title": "Eclipse", "questions": [{"question": "Q1. How can you minimise all views except for the currently selected view in the Eclipse interface?\n", "alternatives": [{"alternative": " Press Control-M (Windows) or Command-M (Mac)\n", "is_correct": false}, {"alternative": " Double-click the tab you want to maximise\n", "is_correct": false}, {"alternative": " all of these answers\n", "is_correct": true}, {"alternative": " Click the Maximise button at the top right of the view\n</ul>\n", "is_correct": false}]}, {"question": "Q2. What happens when you execute the Run -&gt; Skip all Breakpoints command?\n", "alternatives": [{"alternative": " All breakpoints are deleted\n", "is_correct": false}, {"alternative": " none of these answers\n", "is_correct": false}, {"alternative": " All breakpoints will not be fired when debugging and will not cause application execution to suspend\n", "is_correct": true}, {"alternative": " All breakpoints and bookmarks are disabled\n</ul>\n", "is_correct": false}]}, {"question": "Q3. What is not a key part of Eclipse projects and technologies?\n", "alternatives": [{"alternative": " Plug-in Development Environment (PDE)\n", "is_correct": false}, {"alternative": " Eclipse Project\n", "is_correct": false}, {"alternative": " Java Development Toold (JDT)\n", "is_correct": true}, {"alternative": " Eclipse .NET\n</ul>\n", "is_correct": false}]}, {"question": "Q4. Which is a valid way to create a code snippet?\n", "alternatives": [{"alternative": " Right-click the selected code and select Add to Snippets\n", "is_correct": true}, {"alternative": " Drag the code into the snippets view\n", "is_correct": false}, {"alternative": " Click Source -&gt; Snippets -&gt; Create Snippet\n", "is_correct": false}, {"alternative": " With the code selected, click the + button in the Snippets view\n</ul>\n", "is_correct": false}]}, {"question": "Q5. In this image, what does the circled button do?\n", "alternatives": [{"alternative": " It expands the comparison between the two files to include whitespace.\n", "is_correct": false}, {"alternative": " It allows you to delete the line of code to which it is connected.\n", "is_correct": false}, {"alternative": " It allows changes from one version of a file to be applied to another version of the file.\n", "is_correct": true}, {"alternative": " It allows you to merge both lines of code together.\n</ul>\n", "is_correct": false}]}, {"question": "Q6. When inserting a snippet containing variables into a source file, how are values for the variable defined?\n", "alternatives": [{"alternative": " Eclipse fills them in with a drop-down menu of available optons.\n", "is_correct": false}, {"alternative": " They are automatically highlighted in code.\n", "is_correct": true}, {"alternative": " They are populated using environment variables.\n", "is_correct": false}, {"alternative": " You populate them through a pop-up windows.\n</ul>\n", "is_correct": false}]}, {"question": "Q7. How can you create a new Git branch in Eclipse?\n", "alternatives": [{"alternative": " all of these answers\n", "is_correct": true}, {"alternative": " Right-click your project in the Package Explorer and select Team -&gt; Switch To -&gt; New Branch\n", "is_correct": false}, {"alternative": " Click File -&gt; New -&gt; Git -&gt; Branch\n", "is_correct": false}, {"alternative": " Click Source -&gt; Team -&gt; Switch To -&gt; New Branch\n</ul>\n", "is_correct": false}]}, {"question": "Q8. Why might you use the Open Type button?\n", "alternatives": [{"alternative": " to open a file by its name\n", "is_correct": false}, {"alternative": " to search the workbench for a class to open in an editor\n", "is_correct": true}, {"alternative": " to find a string in a text file\n", "is_correct": false}, {"alternative": " to find all places where a certain type is instantiated\n</ul>\n", "is_correct": false}]}, {"question": "Q9. In the JUnit view, what is the value in the parentheses after a previously run unit test?\n", "alternatives": [{"alternative": " the number of errors found in the test\n", "is_correct": false}, {"alternative": " the time it took the test to run\n", "is_correct": true}, {"alternative": " the name of the package containing the test class\n", "is_correct": false}, {"alternative": " the test class name\n</ul>\n", "is_correct": false}]}, {"question": "Q10. In this image, what does the circled icon in the Problems view do?\n", "alternatives": [{"alternative": " It sends the currently selected problem to another view.\n", "is_correct": false}, {"alternative": " It indents the currently selected problem.\n", "is_correct": false}, {"alternative": " It opens the Filter menu so you can customise what problems are displayed.\n", "is_correct": true}, {"alternative": " It jumps to the currently selected problem in the Editor.\n</ul>\n", "is_correct": false}]}, {"question": "Q11. What can you not do in the Expressions view?\n", "alternatives": [{"alternative": " track the value of a variable throughout the lifetime of the app.\n", "is_correct": true}, {"alternative": " change the name of a variable while debugging.\n", "is_correct": false}, {"alternative": " change the value of a final variable while debugging.\n", "is_correct": false}, {"alternative": " track values of variables when they are out of scope.\n</ul>\n", "is_correct": false}]}, {"question": "Q12. Your code is highlighted in red when running code coverage. Why is this?\n", "alternatives": [{"alternative": " The code is the cause of a compiler warning.\n", "is_correct": false}, {"alternative": " The method is unused or causes runtime errors.\n", "is_correct": false}, {"alternative": " The code is within an if statement that is always evaluated as true at runtime.\n", "is_correct": false}, {"alternative": " No code calls the method.\n</ul>\n", "is_correct": true}]}, {"question": "Q13. When selecting the Synchronise Workspace option for a project, what perspective is opened?\n", "alternatives": [{"alternative": " Git\n", "is_correct": false}, {"alternative": " Java\n", "is_correct": false}, {"alternative": " Team Synchronising\n", "is_correct": true}, {"alternative": " Remote Synchronise\n</ul>\n", "is_correct": false}]}, {"question": "Q14. Which is not a way to check the value of a variable while debugging?\n", "alternatives": [{"alternative": " Hover ove the variable in the Editor.\n", "is_correct": false}, {"alternative": " Check the Debug view.\n", "is_correct": false}, {"alternative": " Check the Variables view.\n", "is_correct": false}, {"alternative": " Watch the variable in the Expressions view.\n</ul>\n", "is_correct": true}]}, {"question": "Q15. How can you configure Eclipse to open a webpage in a browser outside of Eclipse using the Windows (Eclipse) -&gt; Preferences -&gt; General -&gt; Web Browser dialog page?\n", "alternatives": [{"alternative": " Select Use external web browser.\n", "is_correct": false}, {"alternative": " Select Add a new browser and select the desired browser in the External web browsers menu.\n", "is_correct": false}, {"alternative": " Select Use external web browser, click the New or Search button, add your browser, and then select it in the External web browsers menu.\n", "is_correct": true}, {"alternative": " Use the Search button to search for an installed web browser.\n</ul>\n", "is_correct": false}]}, {"question": "Q16. What view, within the Team component, displays the commits related to a particular project or file?\n", "alternatives": [{"alternative": " Git Staging\n", "is_correct": false}, {"alternative": " History\n", "is_correct": true}, {"alternative": " Synchronize\n", "is_correct": false}, {"alternative": " Git Repositories\n</ul>\n", "is_correct": false}]}, {"question": "Q17. What is included in your wqorkspace folder?\n", "alternatives": [{"alternative": " a hidden .metadata folder\n", "is_correct": false}, {"alternative": " a hidden .metadata folder and projects imported into the workspace only\n", "is_correct": false}, {"alternative": " only projects imported into the workspace\n", "is_correct": false}, {"alternative": " a hidden .metadata folder and projects created in the workspace\n</ul>\n", "is_correct": true}]}, {"question": "Q18. What can you not do in the Variables view?\n", "alternatives": [{"alternative": " monitor variables that are outside the scope of the current stack frame\n", "is_correct": false}, {"alternative": " set a breakpoint to track a particular instance\n", "is_correct": false}, {"alternative": " inspect the values of an object's fields\n", "is_correct": false}, {"alternative": " edit the value of a variable while the debugger is running your app\n</ul>\n", "is_correct": true}]}, {"question": "Q19. What is not a method stub that Eclipse will create for you in the New JUnit Test Case window?\n", "alternatives": [{"alternative": " tearDown()\n", "is_correct": false}, {"alternative": " setUpClass()\n", "is_correct": true}, {"alternative": " tearDownAfterClass()\n", "is_correct": false}, {"alternative": " setUp()\n</ul>\n", "is_correct": false}]}, {"question": "Q20. What does the Problems view show?\n", "alternatives": [{"alternative": " all of the answers\n", "is_correct": true}, {"alternative": " warnings and errors\n", "is_correct": false}, {"alternative": " code that does not match your formatting settings\n", "is_correct": false}, {"alternative": " threads containing errors\n</ul>\n", "is_correct": false}]}, {"question": "Q21. When switching workspaces, what is preserved?\n", "alternatives": [{"alternative": " all preferences\n", "is_correct": true}, {"alternative": " none of these answers\n", "is_correct": false}, {"alternative": " the current perspective\n", "is_correct": false}, {"alternative": " preferences for a language (e.g., Java)\n</ul>\n", "is_correct": false}]}, {"question": "Q22. How can you set files to save automatically when launching an application?\n", "alternatives": [{"alternative": " Click Window (Eclipse) -&gt; Preferences -&gt; Run/Debug -&gt; Launching, and then select Save required dirty editors before launching.\n", "is_correct": true}, {"alternative": " Click Window (Eclipse) -&gt; Preferences -&gt; Java -&gt; Editor -&gt; Save Actions\n", "is_correct": false}, {"alternative": " Click File -&gt; Save All.\n", "is_correct": false}, {"alternative": " Change the project's run configuration.\n</ul>\n", "is_correct": false}]}, {"question": "Q23. Which is <em>not</em> a valid way to create a test class?\n", "alternatives": [{"alternative": " In the <strong>Package Explorer</strong>, right-click a class and select <strong>New &gt; JUnit Test Case</strong>.\n", "is_correct": false}, {"alternative": " none of these answers\n", "is_correct": true}, {"alternative": " Create a JUnit Test Case class through the <strong>File</strong> menu.\n", "is_correct": false}, {"alternative": " Create the class manually while in any perspective.\n</ul>\n", "is_correct": false}]}, {"question": "Q24. What happens when you double-click a Revision Time in the History view?\n", "alternatives": [{"alternative": " Nothing happens.\n", "is_correct": false}, {"alternative": " The select file is opened in the Editor in its state at the time of the revision.\n", "is_correct": true}, {"alternative": " The revision opens in a <strong>Split Editor</strong> window alongside the current local revision of the file.\n", "is_correct": false}, {"alternative": " A pop-up window showing details about the revision appears.\n</ul>\n", "is_correct": false}]}, {"question": "Q25. What is the benefit of using perspectives?\n", "alternatives": [{"alternative": " to switch between preferences within a single workspace\n", "is_correct": false}, {"alternative": " to easily switch between different layouts of views in the Workbenchfor specific tasks\n", "is_correct": true}, {"alternative": " to manage the fact that some views work only in certain perspectives\n", "is_correct": false}, {"alternative": " to debug multiple applications at the same time\n</ul>\n<p><a href=\"https://www.eclipse.org/articles/using-perspectives/PerspectiveArticle.html\">Reference</a></p>\n", "is_correct": false}]}, {"question": "Q26. When viewing an XML file in Eclipse, how can you view the file in a visual hierarchy (as opposed to code alone)?\n", "alternatives": [{"alternative": " You cannot do this in Eclipse.\n", "is_correct": false}, {"alternative": " Select the Editor tab for the XML file and then click the Design tab at the bottom of the editor window.\n", "is_correct": false}, {"alternative": " Double-click the open tab in the Editor.\n", "is_correct": false}, {"alternative": " In the Package Explorer, right-click the file and select Open With &gt; Desgign Editor.\n</ul>\n", "is_correct": false}]}, {"question": "Q27. How can you view all the commits for a single file?\n", "alternatives": [{"alternative": " Open the commit in the Git Staging view.\n", "is_correct": false}, {"alternative": " Open the commit in the Git Reflog view.\n", "is_correct": false}, {"alternative": " Double-click a commit in the History view.\n", "is_correct": false}, {"alternative": " Right-click the file in the Package Explorer and select Team &gt; Show in History.\n</ul>\n", "is_correct": true}]}, {"question": "Q28. In the image below, what does the circled button do?\n<p><img alt=\"image Q28\" src=\"https://github.com/Beziu/linkedin-skill-assessments-quizzes/blob/master/eclipse/images/Eclipse-Q28.jpg\" /></p>\n", "alternatives": [{"alternative": " It links the Editor and Navigator, causing the Editor to switch to the file selected in the Package Explorer and vice versa.\n", "is_correct": false}, {"alternative": " It expands Libraries when you are in the Java perspective.\n", "is_correct": false}, {"alternative": " It minimizes the left view\n", "is_correct": false}, {"alternative": " It collapses open folders in the Package Explorer view.\n</ul>\n", "is_correct": false}]}, {"question": "Q29. Why might you create multiple debug configurations for the same project?\n", "alternatives": [{"alternative": " all of these answers\n", "is_correct": false}, {"alternative": " to debug using a different JRE\n", "is_correct": false}, {"alternative": " to customize environment variables\n", "is_correct": false}, {"alternative": " to customize arguments\n</ul>\n", "is_correct": false}]}, {"question": "Q30. You are searching for code using the Search dialog, and no results appear. What is a likely cause?\n", "alternatives": [{"alternative": " all of these answers\n", "is_correct": false}, {"alternative": " The scope of the search is too narrow.\n", "is_correct": false}, {"alternative": " The type of search is not appropriate for the language of the code.\n", "is_correct": false}, {"alternative": " There is a typo in the search parameters.\n</ul>\n", "is_correct": false}]}, {"question": "Q31. If you check out a branch in Eclipse and still see the old code, what is one possible problem?\n", "alternatives": [{"alternative": " Your project is not using source control.\n", "is_correct": true}, {"alternative": " Your internet connection is down.\n", "is_correct": false}, {"alternative": " Your Git passwordis incorrect.\n", "is_correct": false}, {"alternative": " You need to refresh your project.\n</ul>\n", "is_correct": false}]}, {"question": "Q32. What is required to create a Git commit?\n", "alternatives": [{"alternative": " all of these answers\n", "is_correct": true}, {"alternative": " a local repository\n", "is_correct": false}, {"alternative": " staged changes\n", "is_correct": false}, {"alternative": " a commit message\n</ul>\n", "is_correct": false}]}, {"question": "Q33. What can you do in the Eclipse Split Editor?\n", "alternatives": [{"alternative": " view the Design and Source tabs of one XML file at the same time\n", "is_correct": false}, {"alternative": " drag code from one Editor pane into another\n", "is_correct": false}, {"alternative": " split the editor either horizontally or vertically\n", "is_correct": false}, {"alternative": " all of these answers\n</ul>\n", "is_correct": false}]}, {"question": "Q34. Why might you run the Project &gt; Clean command?\n", "alternatives": [{"alternative": " to remedy an issue where the source code seemsaccurate, but Git is indicating a merge conflict\n", "is_correct": false}, {"alternative": " to remedy syntax errors within the source code, causing the project not to build\n", "is_correct": false}, {"alternative": " to discard any existing build state before building the project, which can remedy issues where the source code seems accurate yet fails to build\n", "is_correct": false}, {"alternative": " to recompile only the source code files that have changed since the last build, which can shorten the build time for long-running builds\n</ul>\n", "is_correct": false}]}, {"question": "Q35. How can you terminate debugging in the Debug view?\n", "alternatives": [{"alternative": " Right-click an item in the stack trace and select Terminate/Disconnect All.\n", "is_correct": false}, {"alternative": " all of these answers\n", "is_correct": false}, {"alternative": " Right-click your application and select Terminate.\n", "is_correct": false}, {"alternative": " Right-click a thread and select Terminate and Remove.\n</ul>\n", "is_correct": false}]}, {"question": "Q36. How do you connect to and debug a remote Java application/server?\n", "alternatives": [{"alternative": " Click Run &gt; Debug As &gt; Remote Application.\n", "is_correct": false}, {"alternative": " You cannot do this in Eclipse.\n", "is_correct": false}, {"alternative": " Create and run a configuration under Run &gt; Debug Configurations &gt; Remote Java Application.\n", "is_correct": true}, {"alternative": " Click Run &gt; External Tools.\n</ul>\n", "is_correct": false}]}, {"question": "Q37. What is the purpose of adding TODO in a comment?\n", "alternatives": [{"alternative": " It reminds you that you have work to do.\n", "is_correct": false}, {"alternative": " Comments starting with TODO are listed in the Tasks view.\n", "is_correct": true}, {"alternative": " It creates automated email reminders of remaining tasks.\n", "is_correct": false}, {"alternative": " Comments starting with TODO are stored in the Task List view.\n</ul>\n", "is_correct": false}]}, {"question": "Q38. When an assert fails where can you view the expected value as compared with the actual value?\n", "alternatives": [{"alternative": " in the Failure Trace section of the JUnit view\n", "is_correct": true}, {"alternative": " in the Debug view\n", "is_correct": false}, {"alternative": " in the console\n", "is_correct": false}, {"alternative": " in the Outline view\n</ul>\n", "is_correct": false}]}, {"question": "Q39. You want to use Bugzilla for managing tasks. What is a prerequisite?\n", "alternatives": [{"alternative": " Select Bugzilla on the list of repositories in the New Task window.\n", "is_correct": false}, {"alternative": " Add Bugzilla as a task repository.\n", "is_correct": false}, {"alternative": " Install the Bugzilla plug-in.\n", "is_correct": true}, {"alternative": " Create a new local task in the Task List.\n</ul>\n", "is_correct": false}]}, {"question": "Q40. Which of these is/are listed when searching via the Quick Access search bar?\n", "alternatives": [{"alternative": " files in the current workspace\n", "is_correct": false}, {"alternative": " all of these answers\n", "is_correct": true}, {"alternative": " XML attribute values\n", "is_correct": false}, {"alternative": " Java members\n</ul>\n", "is_correct": false}]}, {"question": "Q41. After opening a code file, you notice some of the syntax coloring is missing. What is the most likely problem?\n", "alternatives": [{"alternative": " The code has an error.\n", "is_correct": false}, {"alternative": " The code is in a language that is too new for Eclipse to support.\n", "is_correct": false}, {"alternative": " The code has the wrong file delimiters.\n", "is_correct": false}, {"alternative": " The perspective you are using is out of date.\n</ul>\n", "is_correct": true}]}, {"question": "Q42. When enabled for a specific section, what do the preferences in Java &gt; Editor &gt; Folding control?\n", "alternatives": [{"alternative": " They cause the section of the class to be collapsed when opened in a new editor.\n", "is_correct": true}, {"alternative": " They cause those members to be placed automatically in a superclass, if present.\n", "is_correct": false}, {"alternative": " They cause class members to be automatically ordered in accordance with the preferences.\n", "is_correct": false}, {"alternative": " They cause the source code to autoformat as it is written.\n</ul>\n", "is_correct": false}]}, {"question": "Q43. How can you specify arguments to be passed to an application or virtual machine when it is launched?\n", "alternatives": [{"alternative": " Click Run &gt; Junit Configurations &gt; Arguments.\n", "is_correct": false}, {"alternative": " Click Run &gt; Run Configurations &gt; Arguments.\n", "is_correct": true}, {"alternative": " Right-click the project and select Arguments.\n", "is_correct": false}, {"alternative": " Click Run &gt; Debug Configurations &gt; Arguments.\n</ul>", "is_correct": false}]}]}